abarna_calc07/__init__.py
abarna_calc07/calculator.py
abarna_calc07-0.1.2.dist-info/METADATA
abarna_calc07-0.1.2.dist-info/WHEEL
abarna_calc07-0.1.2.dist-info/top_level.txt
abarna_calc07-0.1.2.dist-info/RECORD
