Metadata-Version: 2.4
Name: abarna_calc07
Version: 0.1.2
Summary: A simple calculator package by Abarna
Home-page: https://github.com/meow074
Author: Abarna
Author-email: abarnamagesh1707@gmail.com
Classifier: Programming Language :: Python :: 3
Classifier: License :: OSI Approved :: MIT License
Classifier: Operating System :: OS Independent
Requires-Python: >=3.6
Dynamic: author
Dynamic: author-email
Dynamic: classifier
Dynamic: description
Dynamic: description-content-type
Dynamic: home-page
Dynamic: requires-python
Dynamic: summary
